{
  "global": {
    "num_points": 6513,
    "avg_pred": 0.1725779210809151,
    "avg_acc": 0.8665745432212498
  },
  "0": {
    "num_points": 1309,
    "avg_pred": 0.04965622612681436,
    "avg_acc": 0.8059587471352178,
    "pred_disc": -0.12292169495410074,
    "acc_disc": -0.06061579608603207,
    "features": [
      {
        "Marital Status": {
          "discrepancy": 0.7318233017422874,
          "values": {
            "Married-civ-spouse": {
              "count": 1080,
              "global": 0.4595424535544296,
              "cluster": 0.825057295645531,
              "discrepancy": 0.3655148420911014
            },
            "Never-married": {
              "count": 45,
              "global": 0.3268846921541532,
              "cluster": 0.03437738731856379,
              "discrepancy": 0.29250730483558945
            },
            "Divorced": {
              "count": 120,
              "global": 0.13327191770305544,
              "cluster": 0.09167303284950344,
              "discrepancy": 0.041598884853551996
            },
            "Separated": {
              "count": 22,
              "global": 0.03408567480423768,
              "cluster": 0.01680672268907563,
              "discrepancy": 0.01727895211516205
            },
            "Widowed": {
              "count": 25,
              "global": 0.03301090127437433,
              "cluster": 0.019098548510313215,
              "discrepancy": 0.013912352764061116
            }
          }
        }
      },
      {
        "Relationship": {
          "discrepancy": 0.7148971728048867,
          "values": {
            "Husband": {
              "count": 961,
              "global": 0.4058037770612621,
              "cluster": 0.73414820473644,
              "discrepancy": 0.32834442767517796
            },
            "Not-in-family": {
              "count": 135,
              "global": 0.25533548288039304,
              "cluster": 0.10313216195569137,
              "discrepancy": 0.15220332092470168
            },
            "Own-child": {
              "count": 25,
              "global": 0.1506218332565638,
              "cluster": 0.019098548510313215,
              "discrepancy": 0.13152328474625058
            },
            "Unmarried": {
              "count": 68,
              "global": 0.10824504836480885,
              "cluster": 0.05194805194805195,
              "discrepancy": 0.056296996416756895
            },
            "Wife": {
              "count": 100,
              "global": 0.04729003531398741,
              "cluster": 0.07639419404125286,
              "discrepancy": 0.029104158727265454
            }
          }
        }
      },
      {
        "Occupation": {
          "discrepancy": 0.3984021144993318,
          "values": {
            "Craft-repair": {
              "count": 304,
              "global": 0.12636265929679102,
              "cluster": 0.2322383498854087,
              "discrepancy": 0.10587569058861768
            },
            "Exec-managerial": {
              "count": 92,
              "global": 0.12743743282665437,
              "cluster": 0.07028265851795264,
              "discrepancy": 0.057154774308701736
            },
            "Prof-specialty": {
              "count": 90,
              "global": 0.1251343466912329,
              "cluster": 0.06875477463712758,
              "discrepancy": 0.056379572054105334
            },
            "Adm-clerical": {
              "count": 107,
              "global": 0.12206356517733763,
              "cluster": 0.08174178762414057,
              "discrepancy": 0.04032177755319706
            },
            "Transport-moving": {
              "count": 105,
              "global": 0.04790419161676647,
              "cluster": 0.08021390374331551,
              "discrepancy": 0.03230971212654904
            }
          }
        }
      },
      {
        "Hours per week": {
          "discrepancy": 0.3414629282892757,
          "values": {
            "40.00133111480863": {
              "count": 810,
              "global": 0.4613849224627668,
              "cluster": 0.6187929717341482,
              "discrepancy": 0.15740804927138136
            },
            "49.99140893470785": {
              "count": 62,
              "global": 0.08935974205435283,
              "cluster": 0.04736440030557677,
              "discrepancy": 0.04199534174877606
            },
            "20.015748031496027": {
              "count": 28,
              "global": 0.03899892522647014,
              "cluster": 0.0213903743315508,
              "discrepancy": 0.017608550894919337
            },
            "60.010204081632594": {
              "count": 37,
              "global": 0.04514048825426071,
              "cluster": 0.02826585179526356,
              "discrepancy": 0.016874636458997148
            },
            "45.035989717223615": {
              "count": 58,
              "global": 0.05972670044526332,
              "cluster": 0.04430863254392666,
              "discrepancy": 0.015418067901336659
            }
          }
        }
      },
      {
        "Education": {
          "discrepancy": 0.32986222419121325,
          "values": {
            "HS-grad": {
              "count": 570,
              "global": 0.32765238753262704,
              "cluster": 0.43544690603514136,
              "discrepancy": 0.10779451850251431
            },
            "Bachelors": {
              "count": 122,
              "global": 0.160908951328113,
              "cluster": 0.0932009167303285,
              "discrepancy": 0.0677080345977845
            },
            "Some-college": {
              "count": 238,
              "global": 0.22570244127130354,
              "cluster": 0.18181818181818182,
              "discrepancy": 0.043884259453121716
            },
            "Masters": {
              "count": 38,
              "global": 0.05189620758483034,
              "cluster": 0.029029793735676088,
              "discrepancy": 0.02286641384915425
            },
            "Prof-school": {
              "count": 5,
              "global": 0.01627514202364502,
              "cluster": 0.0038197097020626434,
              "discrepancy": 0.012455432321582376
            }
          }
        }
      },
      {
        "Education-Num": {
          "discrepancy": 0.32986222419121325,
          "values": {
            "9.0": {
              "count": 570,
              "global": 0.32765238753262704,
              "cluster": 0.43544690603514136,
              "discrepancy": 0.10779451850251431
            },
            "13.0": {
              "count": 122,
              "global": 0.160908951328113,
              "cluster": 0.0932009167303285,
              "discrepancy": 0.0677080345977845
            },
            "10.0": {
              "count": 238,
              "global": 0.22570244127130354,
              "cluster": 0.18181818181818182,
              "discrepancy": 0.043884259453121716
            },
            "14.0": {
              "count": 38,
              "global": 0.05189620758483034,
              "cluster": 0.029029793735676088,
              "discrepancy": 0.02286641384915425
            },
            "15.0": {
              "count": 5,
              "global": 0.01627514202364502,
              "cluster": 0.0038197097020626434,
              "discrepancy": 0.012455432321582376
            }
          }
        }
      },
      {
        "Sex": {
          "discrepancy": 0.29017806192867834,
          "values": {
            "Male": {
              "count": 1065,
              "global": 0.6685091355750038,
              "cluster": 0.813598166539343,
              "discrepancy": 0.14508903096433923
            },
            "Female": {
              "count": 244,
              "global": 0.33149086442499615,
              "cluster": 0.186401833460657,
              "discrepancy": 0.14508903096433914
            }
          }
        }
      },
      {
        "Age": {
          "discrepancy": 0.27242969546597584,
          "values": {
            "17.589473684210596": {
              "count": 1,
              "global": 0.02917242438200522,
              "cluster": 0.0007639419404125286,
              "discrepancy": 0.028408482441592692
            },
            "19.000000000000032": {
              "count": 4,
              "global": 0.022109626900046062,
              "cluster": 0.0030557677616501145,
              "discrepancy": 0.019053859138395947
            },
            "20.00000000000003": {
              "count": 6,
              "global": 0.022570244127130355,
              "cluster": 0.004583651642475172,
              "discrepancy": 0.017986592484655183
            },
            "21.000000000000018": {
              "count": 8,
              "global": 0.022263165975740826,
              "cluster": 0.006111535523300229,
              "discrepancy": 0.0161516304524406
            },
            "43.46623794212218": {
              "count": 82,
              "global": 0.047750652541071706,
              "cluster": 0.06264323911382735,
              "discrepancy": 0.014892586572755648
            }
          }
        }
      },
      {
        "Capital Gain": {
          "discrepancy": 0.1596806387225548,
          "values": {
            "0.01902219266321481": {
              "count": 1309,
              "global": 0.9201596806387226,
              "cluster": 1.0,
              "discrepancy": 0.07984031936127745
            },
            "15023.933333333345": {
              "count": 0,
              "global": 0.009212344541685858,
              "cluster": 0.0,
              "discrepancy": 0.009212344541685858
            },
            "7687.9999999999945": {
              "count": 0,
              "global": 0.008598188238906802,
              "cluster": 0.0,
              "discrepancy": 0.008598188238906802
            },
            "7304.29545454545": {
              "count": 0,
              "global": 0.00675571933056963,
              "cluster": 0.0,
              "discrepancy": 0.00675571933056963
            },
            "99998.99999999996": {
              "count": 0,
              "global": 0.0052203285736219865,
              "cluster": 0.0,
              "discrepancy": 0.0052203285736219865
            }
          }
        }
      },
      {
        "fnlwgt": {
          "discrepancy": 0.1121766574390738,
          "values": {
            "232989.78217821787": {
              "count": 54,
              "global": 0.03101489329034239,
              "cluster": 0.04125286478227655,
              "discrepancy": 0.010237971491934159
            },
            "273286.8834355826": {
              "count": 22,
              "global": 0.025180408413941348,
              "cluster": 0.01680672268907563,
              "discrepancy": 0.008373685724865718
            },
            "379249.2551020407": {
              "count": 30,
              "global": 0.015046829418086903,
              "cluster": 0.02291825821237586,
              "discrepancy": 0.007871428794288957
            },
            "127046.35897435874": {
              "count": 37,
              "global": 0.03592814371257485,
              "cluster": 0.02826585179526356,
              "discrepancy": 0.007662291917311288
            },
            "210199.3925925926": {
              "count": 62,
              "global": 0.041455550437586364,
              "cluster": 0.04736440030557677,
              "discrepancy": 0.0059088498679904095
            }
          }
        }
      },
      {
        "Country": {
          "discrepancy": 0.07553160705679189,
          "values": {
            "United-States": {
              "count": 1149,
              "global": 0.8991248272685398,
              "cluster": 0.8777692895339955,
              "discrepancy": 0.02135553773454435
            },
            "Mexico": {
              "count": 50,
              "global": 0.021188392445877474,
              "cluster": 0.03819709702062643,
              "discrepancy": 0.017008704574748956
            },
            "Italy": {
              "count": 8,
              "global": 0.0027637033625057578,
              "cluster": 0.006111535523300229,
              "discrepancy": 0.0033478321607944713
            },
            "Philippines": {
              "count": 12,
              "global": 0.005834484876401044,
              "cluster": 0.009167303284950344,
              "discrepancy": 0.0033328184085493007
            },
            "China": {
              "count": 6,
              "global": 0.0021495470597267005,
              "cluster": 0.004583651642475172,
              "discrepancy": 0.0024341045827484717
            }
          }
        }
      },
      {
        "Workclass": {
          "discrepancy": 0.059132836167003114,
          "values": {
            "Self-emp-not-inc": {
              "count": 121,
              "global": 0.0761553815446031,
              "cluster": 0.09243697478991597,
              "discrepancy": 0.016281593245312864
            },
            "Private": {
              "count": 903,
              "global": 0.7039766620604944,
              "cluster": 0.6898395721925134,
              "discrepancy": 0.014137089867981012
            },
            "Self-emp-inc": {
              "count": 27,
              "global": 0.032243205895900504,
              "cluster": 0.020626432391138275,
              "discrepancy": 0.011616773504762229
            },
            "?": {
              "count": 83,
              "global": 0.05665591893136803,
              "cluster": 0.06340718105423988,
              "discrepancy": 0.0067512621228718525
            },
            "Local-gov": {
              "count": 89,
              "global": 0.062490403807769074,
              "cluster": 0.06799083269671505,
              "discrepancy": 0.005500428888945974
            }
          }
        }
      },
      {
        "Capital Loss": {
          "discrepancy": 0.04802430163472785,
          "values": {
            "-4.817479748453479e-12": {
              "count": 1268,
              "global": 0.9554736680485183,
              "cluster": 0.9686783804430863,
              "discrepancy": 0.013204712394567997
            },
            "1977.3999999999992": {
              "count": 1,
              "global": 0.006909258406264394,
              "cluster": 0.0007639419404125286,
              "discrepancy": 0.006145316465851865
            },
            "1902.0000000000002": {
              "count": 2,
              "global": 0.006295102103485337,
              "cluster": 0.0015278838808250573,
              "discrepancy": 0.004767218222660279
            },
            "1887.000000000001": {
              "count": 2,
              "global": 0.003992015968063872,
              "cluster": 0.0015278838808250573,
              "discrepancy": 0.0024641320872388147
            },
            "2415.0000000000005": {
              "count": 0,
              "global": 0.0018424689083371719,
              "cluster": 0.0,
              "discrepancy": 0.0018424689083371719
            }
          }
        }
      },
      {
        "Race": {
          "discrepancy": 0.03548805309988823,
          "values": {
            "Black": {
              "count": 105,
              "global": 0.09795793029325964,
              "cluster": 0.08021390374331551,
              "discrepancy": 0.017744026549944128
            },
            "White": {
              "count": 1135,
              "global": 0.8545984953170582,
              "cluster": 0.86707410236822,
              "discrepancy": 0.012475607051161797
            },
            "Other": {
              "count": 16,
              "global": 0.009058805465991094,
              "cluster": 0.012223071046600458,
              "discrepancy": 0.003164265580609364
            },
            "Asian-Pac-Islander": {
              "count": 39,
              "global": 0.028404729003531397,
              "cluster": 0.029793735676088617,
              "discrepancy": 0.00138900667255722
            },
            "Amer-Indian-Eskimo": {
              "count": 14,
              "global": 0.00998003992015968,
              "cluster": 0.0106951871657754,
              "discrepancy": 0.0007151472456157198
            }
          }
        }
      }
    ]
  },
  "1": {
    "num_points": 933,
    "avg_pred": 0.6291532690246516,
    "avg_acc": 0.7041800643086816,
    "pred_disc": 0.45657534794373655,
    "acc_disc": -0.1623944789125682,
    "features": [
      {
        "Education": {
          "discrepancy": 1.2251322238036915,
          "values": {
            "Bachelors": {
              "count": 508,
              "global": 0.160908951328113,
              "cluster": 0.5444801714898178,
              "discrepancy": 0.38357122016170475
            },
            "HS-grad": {
              "count": 36,
              "global": 0.32765238753262704,
              "cluster": 0.03858520900321544,
              "discrepancy": 0.2890671785294116
            },
            "Some-college": {
              "count": 66,
              "global": 0.22570244127130354,
              "cluster": 0.0707395498392283,
              "discrepancy": 0.15496289143207526
            },
            "Masters": {
              "count": 184,
              "global": 0.05189620758483034,
              "cluster": 0.19721329046087888,
              "discrepancy": 0.14531708287604855
            },
            "Prof-school": {
              "count": 58,
              "global": 0.01627514202364502,
              "cluster": 0.06216505894962487,
              "discrepancy": 0.04588991692597985
            }
          }
        }
      },
      {
        "Education-Num": {
          "discrepancy": 1.2251322238036915,
          "values": {
            "13.0": {
              "count": 508,
              "global": 0.160908951328113,
              "cluster": 0.5444801714898178,
              "discrepancy": 0.38357122016170475
            },
            "9.0": {
              "count": 36,
              "global": 0.32765238753262704,
              "cluster": 0.03858520900321544,
              "discrepancy": 0.2890671785294116
            },
            "10.0": {
              "count": 66,
              "global": 0.22570244127130354,
              "cluster": 0.0707395498392283,
              "discrepancy": 0.15496289143207526
            },
            "14.0": {
              "count": 184,
              "global": 0.05189620758483034,
              "cluster": 0.19721329046087888,
              "discrepancy": 0.14531708287604855
            },
            "15.0": {
              "count": 58,
              "global": 0.01627514202364502,
              "cluster": 0.06216505894962487,
              "discrepancy": 0.04588991692597985
            }
          }
        }
      },
      {
        "Relationship": {
          "discrepancy": 0.8880245938990186,
          "values": {
            "Husband": {
              "count": 772,
              "global": 0.4058037770612621,
              "cluster": 0.827438370846731,
              "discrepancy": 0.4216345937854689
            },
            "Not-in-family": {
              "count": 75,
              "global": 0.25533548288039304,
              "cluster": 0.08038585209003216,
              "discrepancy": 0.17494963079036088
            },
            "Own-child": {
              "count": 13,
              "global": 0.1506218332565638,
              "cluster": 0.013933547695605574,
              "discrepancy": 0.13668828556095824
            },
            "Unmarried": {
              "count": 6,
              "global": 0.10824504836480885,
              "cluster": 0.006430868167202572,
              "discrepancy": 0.10181418019760627
            },
            "Other-relative": {
              "count": 2,
              "global": 0.0327038231229848,
              "cluster": 0.0021436227224008574,
              "discrepancy": 0.030560200400583944
            }
          }
        }
      },
      {
        "Marital Status": {
          "discrepancy": 0.8837018024302619,
          "values": {
            "Married-civ-spouse": {
              "count": 841,
              "global": 0.4595424535544296,
              "cluster": 0.9013933547695605,
              "discrepancy": 0.44185090121513093
            },
            "Never-married": {
              "count": 75,
              "global": 0.3268846921541532,
              "cluster": 0.08038585209003216,
              "discrepancy": 0.24649884006412107
            },
            "Divorced": {
              "count": 13,
              "global": 0.13327191770305544,
              "cluster": 0.013933547695605574,
              "discrepancy": 0.11933837000744986
            },
            "Widowed": {
              "count": 0,
              "global": 0.03301090127437433,
              "cluster": 0.0,
              "discrepancy": 0.03301090127437433
            },
            "Separated": {
              "count": 3,
              "global": 0.03408567480423768,
              "cluster": 0.003215434083601286,
              "discrepancy": 0.030870240720636394
            }
          }
        }
      },
      {
        "Occupation": {
          "discrepancy": 0.8185439657415321,
          "values": {
            "Prof-specialty": {
              "count": 321,
              "global": 0.1251343466912329,
              "cluster": 0.3440514469453376,
              "discrepancy": 0.2189171002541047
            },
            "Exec-managerial": {
              "count": 272,
              "global": 0.12743743282665437,
              "cluster": 0.2915326902465166,
              "discrepancy": 0.16409525741986225
            },
            "Other-service": {
              "count": 13,
              "global": 0.10010747735298633,
              "cluster": 0.013933547695605574,
              "discrepancy": 0.08617392965738076
            },
            "Craft-repair": {
              "count": 45,
              "global": 0.12636265929679102,
              "cluster": 0.04823151125401929,
              "discrepancy": 0.07813114804277174
            },
            "Adm-clerical": {
              "count": 46,
              "global": 0.12206356517733763,
              "cluster": 0.04930332261521972,
              "discrepancy": 0.07276024256211791
            }
          }
        }
      },
      {
        "Sex": {
          "discrepancy": 0.4957791565027254,
          "values": {
            "Female": {
              "count": 78,
              "global": 0.33149086442499615,
              "cluster": 0.08360128617363344,
              "discrepancy": 0.2478895782513627
            },
            "Male": {
              "count": 855,
              "global": 0.6685091355750038,
              "cluster": 0.9163987138263665,
              "discrepancy": 0.2478895782513627
            }
          }
        }
      },
      {
        "Age": {
          "discrepancy": 0.44919312994095917,
          "values": {
            "17.589473684210596": {
              "count": 0,
              "global": 0.02917242438200522,
              "cluster": 0.0,
              "discrepancy": 0.02917242438200522
            },
            "22.000000000000014": {
              "count": 0,
              "global": 0.023337939505604175,
              "cluster": 0.0,
              "discrepancy": 0.023337939505604175
            },
            "43.46623794212218": {
              "count": 66,
              "global": 0.047750652541071706,
              "cluster": 0.0707395498392283,
              "discrepancy": 0.02298889729815659
            },
            "20.00000000000003": {
              "count": 0,
              "global": 0.022570244127130355,
              "cluster": 0.0,
              "discrepancy": 0.022570244127130355
            },
            "21.000000000000018": {
              "count": 0,
              "global": 0.022263165975740826,
              "cluster": 0.0,
              "discrepancy": 0.022263165975740826
            }
          }
        }
      },
      {
        "Hours per week": {
          "discrepancy": 0.4275742356494036,
          "values": {
            "49.99140893470785": {
              "count": 168,
              "global": 0.08935974205435283,
              "cluster": 0.18006430868167203,
              "discrepancy": 0.0907045666273192
            },
            "40.00133111480863": {
              "count": 363,
              "global": 0.4613849224627668,
              "cluster": 0.3890675241157556,
              "discrepancy": 0.07231739834701117
            },
            "45.035989717223615": {
              "count": 90,
              "global": 0.05972670044526332,
              "cluster": 0.09646302250803858,
              "discrepancy": 0.03673632206277526
            },
            "60.010204081632594": {
              "count": 76,
              "global": 0.04514048825426071,
              "cluster": 0.08145766345123258,
              "discrepancy": 0.03631717519697187
            },
            "54.92810457516337": {
              "count": 49,
              "global": 0.02349147858129894,
              "cluster": 0.05251875669882101,
              "discrepancy": 0.02902727811752207
            }
          }
        }
      },
      {
        "Workclass": {
          "discrepancy": 0.28164299647057595,
          "values": {
            "Private": {
              "count": 551,
              "global": 0.7039766620604944,
              "cluster": 0.5905680600214362,
              "discrepancy": 0.11340860203905812
            },
            "Self-emp-inc": {
              "count": 80,
              "global": 0.032243205895900504,
              "cluster": 0.0857449088960343,
              "discrepancy": 0.05350170300013379
            },
            "Self-emp-not-inc": {
              "count": 107,
              "global": 0.0761553815446031,
              "cluster": 0.11468381564844587,
              "discrepancy": 0.03852843410384277
            },
            "?": {
              "count": 28,
              "global": 0.05665591893136803,
              "cluster": 0.030010718113612004,
              "discrepancy": 0.026645200817756027
            },
            "State-gov": {
              "count": 56,
              "global": 0.03807769077230155,
              "cluster": 0.06002143622722401,
              "discrepancy": 0.021943745454922454
            }
          }
        }
      },
      {
        "Capital Loss": {
          "discrepancy": 0.2007027251458003,
          "values": {
            "-4.817479748453479e-12": {
              "count": 807,
              "global": 0.9554736680485183,
              "cluster": 0.864951768488746,
              "discrepancy": 0.0905218995597723
            },
            "1902.0000000000002": {
              "count": 31,
              "global": 0.006295102103485337,
              "cluster": 0.03322615219721329,
              "discrepancy": 0.026931050093727954
            },
            "1977.3999999999992": {
              "count": 29,
              "global": 0.006909258406264394,
              "cluster": 0.031082529474812434,
              "discrepancy": 0.02417327106854804
            },
            "1887.000000000001": {
              "count": 20,
              "global": 0.003992015968063872,
              "cluster": 0.021436227224008574,
              "discrepancy": 0.017444211255944704
            },
            "2415.0000000000005": {
              "count": 11,
              "global": 0.0018424689083371719,
              "cluster": 0.011789924973204717,
              "discrepancy": 0.009947456064867546
            }
          }
        }
      },
      {
        "Capital Gain": {
          "discrepancy": 0.1596806387225548,
          "values": {
            "0.01902219266321481": {
              "count": 933,
              "global": 0.9201596806387226,
              "cluster": 1.0,
              "discrepancy": 0.07984031936127745
            },
            "15023.933333333345": {
              "count": 0,
              "global": 0.009212344541685858,
              "cluster": 0.0,
              "discrepancy": 0.009212344541685858
            },
            "7687.9999999999945": {
              "count": 0,
              "global": 0.008598188238906802,
              "cluster": 0.0,
              "discrepancy": 0.008598188238906802
            },
            "7304.29545454545": {
              "count": 0,
              "global": 0.00675571933056963,
              "cluster": 0.0,
              "discrepancy": 0.00675571933056963
            },
            "99998.99999999996": {
              "count": 0,
              "global": 0.0052203285736219865,
              "cluster": 0.0,
              "discrepancy": 0.0052203285736219865
            }
          }
        }
      },
      {
        "fnlwgt": {
          "discrepancy": 0.14459530111185,
          "values": {
            "200307.30630630624": {
              "count": 63,
              "global": 0.051128512206356516,
              "cluster": 0.06752411575562701,
              "discrepancy": 0.0163956035492705
            },
            "97847.07053941913": {
              "count": 44,
              "global": 0.037309995393827726,
              "cluster": 0.04715969989281887,
              "discrepancy": 0.00984970449899114
            },
            "258890.39999999985": {
              "count": 17,
              "global": 0.02594810379241517,
              "cluster": 0.01822079314040729,
              "discrepancy": 0.007727310652007879
            },
            "244637.78974358964": {
              "count": 21,
              "global": 0.029940119760479042,
              "cluster": 0.022508038585209004,
              "discrepancy": 0.007432081175270038
            },
            "35273.43438914072": {
              "count": 38,
              "global": 0.03377859665284815,
              "cluster": 0.04072883172561629,
              "discrepancy": 0.006950235072768138
            }
          }
        }
      },
      {
        "Race": {
          "discrepancy": 0.13967415157318308,
          "values": {
            "Black": {
              "count": 38,
              "global": 0.09795793029325964,
              "cluster": 0.04072883172561629,
              "discrepancy": 0.05722909856764335
            },
            "White": {
              "count": 849,
              "global": 0.8545984953170582,
              "cluster": 0.909967845659164,
              "discrepancy": 0.05536935034210577
            },
            "Asian-Pac-Islander": {
              "count": 40,
              "global": 0.028404729003531397,
              "cluster": 0.04287245444801715,
              "discrepancy": 0.014467725444485751
            },
            "Amer-Indian-Eskimo": {
              "count": 1,
              "global": 0.00998003992015968,
              "cluster": 0.0010718113612004287,
              "discrepancy": 0.008908228558959251
            },
            "Other": {
              "count": 5,
              "global": 0.009058805465991094,
              "cluster": 0.0053590568060021436,
              "discrepancy": 0.0036997486599889507
            }
          }
        }
      },
      {
        "Country": {
          "discrepancy": 0.09467880958340548,
          "values": {
            "?": {
              "count": 28,
              "global": 0.014893290342392139,
              "cluster": 0.030010718113612004,
              "discrepancy": 0.015117427771219865
            },
            "Mexico": {
              "count": 6,
              "global": 0.021188392445877474,
              "cluster": 0.006430868167202572,
              "discrepancy": 0.014757524278674902
            },
            "United-States": {
              "count": 826,
              "global": 0.8991248272685398,
              "cluster": 0.8853161843515541,
              "discrepancy": 0.013808642916985692
            },
            "India": {
              "count": 10,
              "global": 0.002456625211116229,
              "cluster": 0.010718113612004287,
              "discrepancy": 0.008261488400888058
            },
            "Philippines": {
              "count": 9,
              "global": 0.005834484876401044,
              "cluster": 0.00964630225080386,
              "discrepancy": 0.0038118173744028155
            }
          }
        }
      }
    ]
  },
  "2": {
    "num_points": 2673,
    "avg_pred": 0.0007482229704451926,
    "avg_acc": 0.9850355405910961,
    "pred_disc": -0.17182969811046991,
    "acc_disc": 0.11846099736984628,
    "features": [
      {
        "Marital Status": {
          "discrepancy": 0.8921488801728322,
          "values": {
            "Married-civ-spouse": {
              "count": 36,
              "global": 0.4595424535544296,
              "cluster": 0.013468013468013467,
              "discrepancy": 0.4460744400864161
            },
            "Never-married": {
              "count": 1774,
              "global": 0.3268846921541532,
              "cluster": 0.6636737747848859,
              "discrepancy": 0.33678908263073265
            },
            "Divorced": {
              "count": 518,
              "global": 0.13327191770305544,
              "cluster": 0.1937897493453049,
              "discrepancy": 0.06051783164224947
            },
            "Separated": {
              "count": 161,
              "global": 0.03408567480423768,
              "cluster": 0.06023194912083801,
              "discrepancy": 0.026146274316600333
            },
            "Widowed": {
              "count": 134,
              "global": 0.03301090127437433,
              "cluster": 0.05013093901982791,
              "discrepancy": 0.01712003774545358
            }
          }
        }
      },
      {
        "Relationship": {
          "discrepancy": 0.8889784964302596,
          "values": {
            "Husband": {
              "count": 2,
              "global": 0.4058037770612621,
              "cluster": 0.0007482229704451926,
              "discrepancy": 0.4050555540908169
            },
            "Own-child": {
              "count": 881,
              "global": 0.1506218332565638,
              "cluster": 0.32959221848110737,
              "discrepancy": 0.17897038522454356
            },
            "Not-in-family": {
              "count": 1097,
              "global": 0.25533548288039304,
              "cluster": 0.4104002992891882,
              "discrepancy": 0.15506481640879516
            },
            "Unmarried": {
              "count": 504,
              "global": 0.10824504836480885,
              "cluster": 0.18855218855218855,
              "discrepancy": 0.08030714018737971
            },
            "Wife": {
              "count": 21,
              "global": 0.04729003531398741,
              "cluster": 0.007856341189674524,
              "discrepancy": 0.039433694124312885
            }
          }
        }
      },
      {
        "Age": {
          "discrepancy": 0.46912373991548967,
          "values": {
            "17.589473684210596": {
              "count": 180,
              "global": 0.02917242438200522,
              "cluster": 0.06734006734006734,
              "discrepancy": 0.03816764295806212
            },
            "19.000000000000032": {
              "count": 133,
              "global": 0.022109626900046062,
              "cluster": 0.049756827534605315,
              "discrepancy": 0.027647200634559253
            },
            "20.00000000000003": {
              "count": 134,
              "global": 0.022570244127130355,
              "cluster": 0.05013093901982791,
              "discrepancy": 0.027560694892697555
            },
            "23.00000000000003": {
              "count": 145,
              "global": 0.027637033625057577,
              "cluster": 0.05424616535727647,
              "discrepancy": 0.026609131732218894
            },
            "22.000000000000014": {
              "count": 132,
              "global": 0.023337939505604175,
              "cluster": 0.04938271604938271,
              "discrepancy": 0.026044776543778538
            }
          }
        }
      },
      {
        "Sex": {
          "discrepancy": 0.4122146796797495,
          "values": {
            "Female": {
              "count": 1437,
              "global": 0.33149086442499615,
              "cluster": 0.5375982042648709,
              "discrepancy": 0.20610733983987478
            },
            "Male": {
              "count": 1236,
              "global": 0.6685091355750038,
              "cluster": 0.4624017957351291,
              "discrepancy": 0.20610733983987473
            }
          }
        }
      },
      {
        "Occupation": {
          "discrepancy": 0.4066441924060021,
          "values": {
            "Other-service": {
              "count": 494,
              "global": 0.10010747735298633,
              "cluster": 0.18481107369996258,
              "discrepancy": 0.08470359634697625
            },
            "Exec-managerial": {
              "count": 135,
              "global": 0.12743743282665437,
              "cluster": 0.050505050505050504,
              "discrepancy": 0.07693238232160388
            },
            "Prof-specialty": {
              "count": 149,
              "global": 0.1251343466912329,
              "cluster": 0.05574261129816686,
              "discrepancy": 0.06939173539306606
            },
            "Adm-clerical": {
              "count": 502,
              "global": 0.12206356517733763,
              "cluster": 0.18780396558174337,
              "discrepancy": 0.06574040040440574
            },
            "Craft-repair": {
              "count": 254,
              "global": 0.12636265929679102,
              "cluster": 0.09502431724653947,
              "discrepancy": 0.03133834205025156
            }
          }
        }
      },
      {
        "Hours per week": {
          "discrepancy": 0.35110164717616477,
          "values": {
            "49.99140893470785": {
              "count": 73,
              "global": 0.08935974205435283,
              "cluster": 0.027310138421249533,
              "discrepancy": 0.0620496036331033
            },
            "40.00133111480863": {
              "count": 1323,
              "global": 0.4613849224627668,
              "cluster": 0.494949494949495,
              "discrepancy": 0.03356457248672817
            },
            "20.015748031496027": {
              "count": 185,
              "global": 0.03899892522647014,
              "cluster": 0.06921062476618033,
              "discrepancy": 0.030211699539710188
            },
            "60.010204081632594": {
              "count": 40,
              "global": 0.04514048825426071,
              "cluster": 0.014964459408903853,
              "discrepancy": 0.030176028845356855
            },
            "45.035989717223615": {
              "count": 80,
              "global": 0.05972670044526332,
              "cluster": 0.029928918817807706,
              "discrepancy": 0.029797781627455614
            }
          }
        }
      },
      {
        "Education": {
          "discrepancy": 0.3155195264310367,
          "values": {
            "Bachelors": {
              "count": 199,
              "global": 0.160908951328113,
              "cluster": 0.07444818555929666,
              "discrepancy": 0.08646076576881634
            },
            "HS-grad": {
              "count": 1059,
              "global": 0.32765238753262704,
              "cluster": 0.3961840628507295,
              "discrepancy": 0.06853167531810245
            },
            "Some-college": {
              "count": 714,
              "global": 0.22570244127130354,
              "cluster": 0.2671156004489338,
              "discrepancy": 0.04141315917763025
            },
            "Masters": {
              "count": 33,
              "global": 0.05189620758483034,
              "cluster": 0.012345679012345678,
              "discrepancy": 0.03955052857248466
            },
            "11th": {
              "count": 150,
              "global": 0.03638876093965914,
              "cluster": 0.05611672278338945,
              "discrepancy": 0.01972796184373031
            }
          }
        }
      },
      {
        "Education-Num": {
          "discrepancy": 0.3155195264310367,
          "values": {
            "13.0": {
              "count": 199,
              "global": 0.160908951328113,
              "cluster": 0.07444818555929666,
              "discrepancy": 0.08646076576881634
            },
            "9.0": {
              "count": 1059,
              "global": 0.32765238753262704,
              "cluster": 0.3961840628507295,
              "discrepancy": 0.06853167531810245
            },
            "10.0": {
              "count": 714,
              "global": 0.22570244127130354,
              "cluster": 0.2671156004489338,
              "discrepancy": 0.04141315917763025
            },
            "14.0": {
              "count": 33,
              "global": 0.05189620758483034,
              "cluster": 0.012345679012345678,
              "discrepancy": 0.03955052857248466
            },
            "7.0": {
              "count": 150,
              "global": 0.03638876093965914,
              "cluster": 0.05611672278338945,
              "discrepancy": 0.01972796184373031
            }
          }
        }
      },
      {
        "Workclass": {
          "discrepancy": 0.16791522713013074,
          "values": {
            "Private": {
              "count": 2057,
              "global": 0.7039766620604944,
              "cluster": 0.7695473251028807,
              "discrepancy": 0.06557066304238635
            },
            "Self-emp-not-inc": {
              "count": 95,
              "global": 0.0761553815446031,
              "cluster": 0.03554059109614665,
              "discrepancy": 0.04061479044845646
            },
            "Self-emp-inc": {
              "count": 23,
              "global": 0.032243205895900504,
              "cluster": 0.008604564160119716,
              "discrepancy": 0.023638641735780785
            },
            "?": {
              "count": 200,
              "global": 0.05665591893136803,
              "cluster": 0.07482229704451927,
              "discrepancy": 0.018166378113151242
            },
            "Local-gov": {
              "count": 129,
              "global": 0.062490403807769074,
              "cluster": 0.04826038159371493,
              "discrepancy": 0.014230022214054144
            }
          }
        }
      },
      {
        "Capital Gain": {
          "discrepancy": 0.15893241575210962,
          "values": {
            "0.01902219266321481": {
              "count": 2672,
              "global": 0.9201596806387226,
              "cluster": 0.9996258885147774,
              "discrepancy": 0.07946620787605485
            },
            "15023.933333333345": {
              "count": 0,
              "global": 0.009212344541685858,
              "cluster": 0.0,
              "discrepancy": 0.009212344541685858
            },
            "7687.9999999999945": {
              "count": 0,
              "global": 0.008598188238906802,
              "cluster": 0.0,
              "discrepancy": 0.008598188238906802
            },
            "7304.29545454545": {
              "count": 0,
              "global": 0.00675571933056963,
              "cluster": 0.0,
              "discrepancy": 0.00675571933056963
            },
            "99998.99999999996": {
              "count": 0,
              "global": 0.0052203285736219865,
              "cluster": 0.0,
              "discrepancy": 0.0052203285736219865
            }
          }
        }
      },
      {
        "Race": {
          "discrepancy": 0.1065033879405137,
          "values": {
            "White": {
              "count": 2142,
              "global": 0.8545984953170582,
              "cluster": 0.8013468013468014,
              "discrepancy": 0.053251693970256864
            },
            "Black": {
              "count": 388,
              "global": 0.09795793029325964,
              "cluster": 0.14515525626636738,
              "discrepancy": 0.047197325973107745
            },
            "Amer-Indian-Eskimo": {
              "count": 37,
              "global": 0.00998003992015968,
              "cluster": 0.013842124953236064,
              "discrepancy": 0.003862085033076383
            },
            "Asian-Pac-Islander": {
              "count": 80,
              "global": 0.028404729003531397,
              "cluster": 0.029928918817807706,
              "discrepancy": 0.0015241898142763083
            },
            "Other": {
              "count": 26,
              "global": 0.009058805465991094,
              "cluster": 0.009726898615787506,
              "discrepancy": 0.0006680931497964112
            }
          }
        }
      },
      {
        "fnlwgt": {
          "discrepancy": 0.09049120958635266,
          "values": {
            "200307.30630630624": {
              "count": 112,
              "global": 0.051128512206356516,
              "cluster": 0.041900486344930786,
              "discrepancy": 0.00922802586142573
            },
            "258890.39999999985": {
              "count": 88,
              "global": 0.02594810379241517,
              "cluster": 0.03292181069958848,
              "discrepancy": 0.006973706907173312
            },
            "155456.23004694842": {
              "count": 71,
              "global": 0.0327038231229848,
              "cluster": 0.02656191545080434,
              "discrepancy": 0.006141907672180463
            },
            "97847.07053941913": {
              "count": 86,
              "global": 0.037309995393827726,
              "cluster": 0.032173587729143284,
              "discrepancy": 0.005136407664684442
            },
            "301737.7295081965": {
              "count": 63,
              "global": 0.018731767234761245,
              "cluster": 0.02356902356902357,
              "discrepancy": 0.004837256334262324
            }
          }
        }
      },
      {
        "Capital Loss": {
          "discrepancy": 0.06391568068214774,
          "values": {
            "-4.817479748453479e-12": {
              "count": 2631,
              "global": 0.9554736680485183,
              "cluster": 0.9842873176206509,
              "discrepancy": 0.028813649572132616
            },
            "1902.0000000000002": {
              "count": 0,
              "global": 0.006295102103485337,
              "cluster": 0.0,
              "discrepancy": 0.006295102103485337
            },
            "1887.000000000001": {
              "count": 0,
              "global": 0.003992015968063872,
              "cluster": 0.0,
              "discrepancy": 0.003992015968063872
            },
            "1977.3999999999992": {
              "count": 9,
              "global": 0.006909258406264394,
              "cluster": 0.003367003367003367,
              "discrepancy": 0.0035422550392610274
            },
            "2415.0000000000005": {
              "count": 0,
              "global": 0.0018424689083371719,
              "cluster": 0.0,
              "discrepancy": 0.0018424689083371719
            }
          }
        }
      },
      {
        "Country": {
          "discrepancy": 0.034243866579195856,
          "values": {
            "United-States": {
              "count": 2390,
              "global": 0.8991248272685398,
              "cluster": 0.8941264496820053,
              "discrepancy": 0.0049983775865345415
            },
            "Mexico": {
              "count": 69,
              "global": 0.021188392445877474,
              "cluster": 0.025813692480359147,
              "discrepancy": 0.004625300034481673
            },
            "El-Salvador": {
              "count": 15,
              "global": 0.003377859665284815,
              "cluster": 0.005611672278338945,
              "discrepancy": 0.0022338126130541295
            },
            "?": {
              "count": 35,
              "global": 0.014893290342392139,
              "cluster": 0.013093901982790871,
              "discrepancy": 0.0017993883596012679
            },
            "Germany": {
              "count": 5,
              "global": 0.003531398740979579,
              "cluster": 0.0018705574261129816,
              "discrepancy": 0.0016608413148665976
            }
          }
        }
      }
    ]
  },
  "3": {
    "num_points": 1078,
    "avg_pred": 0.16326530612244897,
    "avg_acc": 0.7551020408163265,
    "pred_disc": -0.009312614958466137,
    "acc_disc": -0.11147250240492335,
    "features": [
      {
        "Hours per week": {
          "discrepancy": 0.6504074767547822,
          "values": {
            "40.00133111480863": {
              "count": 307,
              "global": 0.4613849224627668,
              "cluster": 0.2847866419294991,
              "discrepancy": 0.1765982805332677
            },
            "49.99140893470785": {
              "count": 195,
              "global": 0.08935974205435283,
              "cluster": 0.18089053803339517,
              "discrepancy": 0.09153079597904233
            },
            "60.010204081632594": {
              "count": 108,
              "global": 0.04514048825426071,
              "cluster": 0.10018552875695733,
              "discrepancy": 0.05504504050269662
            },
            "45.035989717223615": {
              "count": 117,
              "global": 0.05972670044526332,
              "cluster": 0.10853432282003711,
              "discrepancy": 0.04880762237477379
            },
            "20.015748031496027": {
              "count": 11,
              "global": 0.03899892522647014,
              "cluster": 0.01020408163265306,
              "discrepancy": 0.02879484359381708
            }
          }
        }
      },
      {
        "Marital Status": {
          "discrepancy": 0.4046865595197502,
          "values": {
            "Never-married": {
              "count": 146,
              "global": 0.3268846921541532,
              "cluster": 0.13543599257884972,
              "discrepancy": 0.1914486995753035
            },
            "Married-civ-spouse": {
              "count": 698,
              "global": 0.4595424535544296,
              "cluster": 0.647495361781076,
              "discrepancy": 0.18795290822664645
            },
            "Separated": {
              "count": 25,
              "global": 0.03408567480423768,
              "cluster": 0.023191094619666047,
              "discrepancy": 0.010894580184571633
            },
            "Divorced": {
              "count": 152,
              "global": 0.13327191770305544,
              "cluster": 0.14100185528756956,
              "discrepancy": 0.007729937584514124
            },
            "Widowed": {
              "count": 41,
              "global": 0.03301090127437433,
              "cluster": 0.038033395176252316,
              "discrepancy": 0.005022493901877985
            }
          }
        }
      },
      {
        "Age": {
          "discrepancy": 0.39273728837458516,
          "values": {
            "17.589473684210596": {
              "count": 4,
              "global": 0.02917242438200522,
              "cluster": 0.0037105751391465678,
              "discrepancy": 0.025461849242858655
            },
            "23.00000000000003": {
              "count": 3,
              "global": 0.027637033625057577,
              "cluster": 0.0027829313543599257,
              "discrepancy": 0.02485410227069765
            },
            "20.00000000000003": {
              "count": 3,
              "global": 0.022570244127130355,
              "cluster": 0.0027829313543599257,
              "discrepancy": 0.01978731277277043
            },
            "21.000000000000018": {
              "count": 4,
              "global": 0.022263165975740826,
              "cluster": 0.0037105751391465678,
              "discrepancy": 0.01855259083659426
            },
            "25.0": {
              "count": 9,
              "global": 0.026408721019499464,
              "cluster": 0.008348794063079777,
              "discrepancy": 0.018059926956419687
            }
          }
        }
      },
      {
        "Relationship": {
          "discrepancy": 0.3888030988116532,
          "values": {
            "Husband": {
              "count": 612,
              "global": 0.4058037770612621,
              "cluster": 0.5677179962894249,
              "discrepancy": 0.1619142192281628
            },
            "Own-child": {
              "count": 39,
              "global": 0.1506218332565638,
              "cluster": 0.036178107606679034,
              "discrepancy": 0.11444372564988478
            },
            "Not-in-family": {
              "count": 235,
              "global": 0.25533548288039304,
              "cluster": 0.21799628942486085,
              "discrepancy": 0.03733919345553219
            },
            "Wife": {
              "count": 86,
              "global": 0.04729003531398741,
              "cluster": 0.07977736549165121,
              "discrepancy": 0.0324873301776638
            },
            "Unmarried": {
              "count": 92,
              "global": 0.10824504836480885,
              "cluster": 0.08534322820037106,
              "discrepancy": 0.022901820164437786
            }
          }
        }
      },
      {
        "Occupation": {
          "discrepancy": 0.3467974853774684,
          "values": {
            "Exec-managerial": {
              "count": 233,
              "global": 0.12743743282665437,
              "cluster": 0.21614100185528756,
              "discrepancy": 0.08870356902863319
            },
            "Other-service": {
              "count": 19,
              "global": 0.10010747735298633,
              "cluster": 0.017625231910946195,
              "discrepancy": 0.08248224544204014
            },
            "Adm-clerical": {
              "count": 88,
              "global": 0.12206356517733763,
              "cluster": 0.08163265306122448,
              "discrepancy": 0.040430912116113146
            },
            "Craft-repair": {
              "count": 167,
              "global": 0.12636265929679102,
              "cluster": 0.1549165120593692,
              "discrepancy": 0.028553852762578186
            },
            "Transport-moving": {
              "count": 82,
              "global": 0.04790419161676647,
              "cluster": 0.07606679035250463,
              "discrepancy": 0.028162598735738162
            }
          }
        }
      },
      {
        "Education": {
          "discrepancy": 0.31416630133482143,
          "values": {
            "Some-college": {
              "count": 357,
              "global": 0.22570244127130354,
              "cluster": 0.33116883116883117,
              "discrepancy": 0.10546638989752763
            },
            "Bachelors": {
              "count": 102,
              "global": 0.160908951328113,
              "cluster": 0.09461966604823747,
              "discrepancy": 0.06628928527987553
            },
            "Assoc-voc": {
              "count": 75,
              "global": 0.04099493321050207,
              "cluster": 0.06957328385899815,
              "discrepancy": 0.02857835064849608
            },
            "Masters": {
              "count": 32,
              "global": 0.05189620758483034,
              "cluster": 0.029684601113172542,
              "discrepancy": 0.022211606471657794
            },
            "11th": {
              "count": 16,
              "global": 0.03638876093965914,
              "cluster": 0.014842300556586271,
              "discrepancy": 0.02154646038307287
            }
          }
        }
      },
      {
        "Education-Num": {
          "discrepancy": 0.31416630133482143,
          "values": {
            "10.0": {
              "count": 357,
              "global": 0.22570244127130354,
              "cluster": 0.33116883116883117,
              "discrepancy": 0.10546638989752763
            },
            "13.0": {
              "count": 102,
              "global": 0.160908951328113,
              "cluster": 0.09461966604823747,
              "discrepancy": 0.06628928527987553
            },
            "11.0": {
              "count": 75,
              "global": 0.04099493321050207,
              "cluster": 0.06957328385899815,
              "discrepancy": 0.02857835064849608
            },
            "14.0": {
              "count": 32,
              "global": 0.05189620758483034,
              "cluster": 0.029684601113172542,
              "discrepancy": 0.022211606471657794
            },
            "7.0": {
              "count": 16,
              "global": 0.03638876093965914,
              "cluster": 0.014842300556586271,
              "discrepancy": 0.02154646038307287
            }
          }
        }
      },
      {
        "Capital Gain": {
          "discrepancy": 0.1596806387225548,
          "values": {
            "0.01902219266321481": {
              "count": 1078,
              "global": 0.9201596806387226,
              "cluster": 1.0,
              "discrepancy": 0.07984031936127745
            },
            "15023.933333333345": {
              "count": 0,
              "global": 0.009212344541685858,
              "cluster": 0.0,
              "discrepancy": 0.009212344541685858
            },
            "7687.9999999999945": {
              "count": 0,
              "global": 0.008598188238906802,
              "cluster": 0.0,
              "discrepancy": 0.008598188238906802
            },
            "7304.29545454545": {
              "count": 0,
              "global": 0.00675571933056963,
              "cluster": 0.0,
              "discrepancy": 0.00675571933056963
            },
            "99998.99999999996": {
              "count": 0,
              "global": 0.0052203285736219865,
              "cluster": 0.0,
              "discrepancy": 0.0052203285736219865
            }
          }
        }
      },
      {
        "Sex": {
          "discrepancy": 0.14721178450861938,
          "values": {
            "Female": {
              "count": 278,
              "global": 0.33149086442499615,
              "cluster": 0.25788497217068646,
              "discrepancy": 0.07360589225430969
            },
            "Male": {
              "count": 800,
              "global": 0.6685091355750038,
              "cluster": 0.7421150278293135,
              "discrepancy": 0.07360589225430969
            }
          }
        }
      },
      {
        "fnlwgt": {
          "discrepancy": 0.1220262486301836,
          "values": {
            "200307.30630630624": {
              "count": 65,
              "global": 0.051128512206356516,
              "cluster": 0.06029684601113173,
              "discrepancy": 0.009168333804775212
            },
            "26647.598360655684": {
              "count": 30,
              "global": 0.019038845386150777,
              "cluster": 0.027829313543599257,
              "discrepancy": 0.00879046815744848
            },
            "360980.5578947365": {
              "count": 24,
              "global": 0.01458621219100261,
              "cluster": 0.022263450834879406,
              "discrepancy": 0.007677238643876795
            },
            "232989.78217821787": {
              "count": 27,
              "global": 0.03101489329034239,
              "cluster": 0.02504638218923933,
              "discrepancy": 0.005968511101103059
            },
            "301737.7295081965": {
              "count": 14,
              "global": 0.018731767234761245,
              "cluster": 0.012987012987012988,
              "discrepancy": 0.005744754247748257
            }
          }
        }
      },
      {
        "Workclass": {
          "discrepancy": 0.10978699088194382,
          "values": {
            "Self-emp-not-inc": {
              "count": 125,
              "global": 0.0761553815446031,
              "cluster": 0.11595547309833024,
              "discrepancy": 0.03980009155372713
            },
            "Private": {
              "count": 731,
              "global": 0.7039766620604944,
              "cluster": 0.6781076066790352,
              "discrepancy": 0.025869055381459116
            },
            "?": {
              "count": 36,
              "global": 0.05665591893136803,
              "cluster": 0.03339517625231911,
              "discrepancy": 0.023260742679048922
            },
            "Self-emp-inc": {
              "count": 44,
              "global": 0.032243205895900504,
              "cluster": 0.04081632653061224,
              "discrepancy": 0.008573120634711738
            },
            "Local-gov": {
              "count": 74,
              "global": 0.062490403807769074,
              "cluster": 0.0686456400742115,
              "discrepancy": 0.006155236266442432
            }
          }
        }
      },
      {
        "Race": {
          "discrepancy": 0.09599781456068879,
          "values": {
            "White": {
              "count": 973,
              "global": 0.8545984953170582,
              "cluster": 0.9025974025974026,
              "discrepancy": 0.047998907280344394
            },
            "Black": {
              "count": 71,
              "global": 0.09795793029325964,
              "cluster": 0.06586270871985157,
              "discrepancy": 0.032095221573408064
            },
            "Asian-Pac-Islander": {
              "count": 16,
              "global": 0.028404729003531397,
              "cluster": 0.014842300556586271,
              "discrepancy": 0.013562428446945126
            },
            "Amer-Indian-Eskimo": {
              "count": 9,
              "global": 0.00998003992015968,
              "cluster": 0.008348794063079777,
              "discrepancy": 0.0016312458570799035
            },
            "Other": {
              "count": 9,
              "global": 0.009058805465991094,
              "cluster": 0.008348794063079777,
              "discrepancy": 0.0007100114029113171
            }
          }
        }
      },
      {
        "Country": {
          "discrepancy": 0.08818156465718487,
          "values": {
            "United-States": {
              "count": 1008,
              "global": 0.8991248272685398,
              "cluster": 0.935064935064935,
              "discrepancy": 0.035940107796395226
            },
            "Mexico": {
              "count": 8,
              "global": 0.021188392445877474,
              "cluster": 0.0074211502782931356,
              "discrepancy": 0.013767242167584338
            },
            "?": {
              "count": 9,
              "global": 0.014893290342392139,
              "cluster": 0.008348794063079777,
              "discrepancy": 0.006544496279312362
            },
            "Philippines": {
              "count": 3,
              "global": 0.005834484876401044,
              "cluster": 0.0027829313543599257,
              "discrepancy": 0.003051553522041118
            },
            "China": {
              "count": 0,
              "global": 0.0021495470597267005,
              "cluster": 0.0,
              "discrepancy": 0.0021495470597267005
            }
          }
        }
      },
      {
        "Capital Loss": {
          "discrepancy": 0.07274077505044145,
          "values": {
            "-4.817479748453479e-12": {
              "count": 997,
              "global": 0.9554736680485183,
              "cluster": 0.924860853432282,
              "discrepancy": 0.030612814616236328
            },
            "1740.0000000000002": {
              "count": 7,
              "global": 0.001996007984031936,
              "cluster": 0.006493506493506494,
              "discrepancy": 0.004497498509474558
            },
            "1670.7999999999997": {
              "count": 6,
              "global": 0.0015353907569476432,
              "cluster": 0.0055658627087198514,
              "discrepancy": 0.004030471951772209
            },
            "1875.9999999999998": {
              "count": 5,
              "global": 0.0010747735298633502,
              "cluster": 0.00463821892393321,
              "discrepancy": 0.0035634453940698594
            },
            "1486.8999999999996": {
              "count": 4,
              "global": 0.0015353907569476432,
              "cluster": 0.0037105751391465678,
              "discrepancy": 0.0021751843821989246
            }
          }
        }
      }
    ]
  },
  "4": {
    "num_points": 520,
    "avg_pred": 0.5653846153846154,
    "avg_acc": 0.9326923076923077,
    "pred_disc": 0.3928066943037003,
    "acc_disc": 0.06611776447105788,
    "features": [
      {
        "Capital Gain": {
          "discrepancy": 1.8364732074312913,
          "values": {
            "0.01902219266321481": {
              "count": 1,
              "global": 0.9201596806387226,
              "cluster": 0.0019230769230769232,
              "discrepancy": 0.9182366037156456
            },
            "15023.933333333345": {
              "count": 60,
              "global": 0.009212344541685858,
              "cluster": 0.11538461538461539,
              "discrepancy": 0.10617227084292953
            },
            "7687.9999999999945": {
              "count": 56,
              "global": 0.008598188238906802,
              "cluster": 0.1076923076923077,
              "discrepancy": 0.0990941194534009
            },
            "7304.29545454545": {
              "count": 44,
              "global": 0.00675571933056963,
              "cluster": 0.08461538461538462,
              "discrepancy": 0.07785966528481499
            },
            "99998.99999999996": {
              "count": 34,
              "global": 0.0052203285736219865,
              "cluster": 0.06538461538461539,
              "discrepancy": 0.0601642868109934
            }
          }
        }
      },
      {
        "Age": {
          "discrepancy": 0.3810532780592661,
          "values": {
            "22.000000000000014": {
              "count": 0,
              "global": 0.023337939505604175,
              "cluster": 0.0,
              "discrepancy": 0.023337939505604175
            },
            "51.48598130841124": {
              "count": 29,
              "global": 0.03285736219867957,
              "cluster": 0.05576923076923077,
              "discrepancy": 0.022911868570551205
            },
            "69.32051282051283": {
              "count": 17,
              "global": 0.011976047904191617,
              "cluster": 0.032692307692307694,
              "discrepancy": 0.020716259788116077
            },
            "64.54216867469879": {
              "count": 17,
              "global": 0.012743743282665438,
              "cluster": 0.032692307692307694,
              "discrepancy": 0.019948564409642256
            },
            "17.589473684210596": {
              "count": 5,
              "global": 0.02917242438200522,
              "cluster": 0.009615384615384616,
              "discrepancy": 0.019557039766620606
            }
          }
        }
      },
      {
        "Marital Status": {
          "discrepancy": 0.3809150928911409,
          "values": {
            "Married-civ-spouse": {
              "count": 338,
              "global": 0.4595424535544296,
              "cluster": 0.65,
              "discrepancy": 0.19045754644557045
            },
            "Never-married": {
              "count": 89,
              "global": 0.3268846921541532,
              "cluster": 0.17115384615384616,
              "discrepancy": 0.15573084600030707
            },
            "Separated": {
              "count": 11,
              "global": 0.03408567480423768,
              "cluster": 0.021153846153846155,
              "discrepancy": 0.012931828650391525
            },
            "Married-spouse-absent": {
              "count": 2,
              "global": 0.012590204206970674,
              "cluster": 0.0038461538461538464,
              "discrepancy": 0.008744050360816828
            },
            "Divorced": {
              "count": 65,
              "global": 0.13327191770305544,
              "cluster": 0.125,
              "discrepancy": 0.008271917703055437
            }
          }
        }
      },
      {
        "Relationship": {
          "discrepancy": 0.3707354521725779,
          "values": {
            "Husband": {
              "count": 296,
              "global": 0.4058037770612621,
              "cluster": 0.5692307692307692,
              "discrepancy": 0.16342699216950712
            },
            "Own-child": {
              "count": 23,
              "global": 0.1506218332565638,
              "cluster": 0.04423076923076923,
              "discrepancy": 0.10639106402579457
            },
            "Unmarried": {
              "count": 35,
              "global": 0.10824504836480885,
              "cluster": 0.0673076923076923,
              "discrepancy": 0.04093735605711654
            },
            "Not-in-family": {
              "count": 121,
              "global": 0.25533548288039304,
              "cluster": 0.2326923076923077,
              "discrepancy": 0.02264317518808534
            },
            "Wife": {
              "count": 36,
              "global": 0.04729003531398741,
              "cluster": 0.06923076923076923,
              "discrepancy": 0.021940733916781828
            }
          }
        }
      },
      {
        "Occupation": {
          "discrepancy": 0.3429295255642561,
          "values": {
            "Prof-specialty": {
              "count": 110,
              "global": 0.1251343466912329,
              "cluster": 0.21153846153846154,
              "discrepancy": 0.08640411484722862
            },
            "Other-service": {
              "count": 17,
              "global": 0.10010747735298633,
              "cluster": 0.032692307692307694,
              "discrepancy": 0.06741516966067865
            },
            "Exec-managerial": {
              "count": 98,
              "global": 0.12743743282665437,
              "cluster": 0.18846153846153846,
              "discrepancy": 0.061024105634884085
            },
            "Craft-repair": {
              "count": 53,
              "global": 0.12636265929679102,
              "cluster": 0.10192307692307692,
              "discrepancy": 0.024439582373714103
            },
            "Adm-clerical": {
              "count": 52,
              "global": 0.12206356517733763,
              "cluster": 0.1,
              "discrepancy": 0.022063565177337624
            }
          }
        }
      },
      {
        "Education": {
          "discrepancy": 0.33141409488714885,
          "values": {
            "HS-grad": {
              "count": 134,
              "global": 0.32765238753262704,
              "cluster": 0.25769230769230766,
              "discrepancy": 0.06996007984031938
            },
            "Bachelors": {
              "count": 117,
              "global": 0.160908951328113,
              "cluster": 0.225,
              "discrepancy": 0.064091048671887
            },
            "Masters": {
              "count": 51,
              "global": 0.05189620758483034,
              "cluster": 0.09807692307692308,
              "discrepancy": 0.04618071549209274
            },
            "Some-college": {
              "count": 95,
              "global": 0.22570244127130354,
              "cluster": 0.18269230769230768,
              "discrepancy": 0.04301013357899586
            },
            "Prof-school": {
              "count": 26,
              "global": 0.01627514202364502,
              "cluster": 0.05,
              "discrepancy": 0.03372485797635498
            }
          }
        }
      },
      {
        "Education-Num": {
          "discrepancy": 0.33141409488714885,
          "values": {
            "9.0": {
              "count": 134,
              "global": 0.32765238753262704,
              "cluster": 0.25769230769230766,
              "discrepancy": 0.06996007984031938
            },
            "13.0": {
              "count": 117,
              "global": 0.160908951328113,
              "cluster": 0.225,
              "discrepancy": 0.064091048671887
            },
            "14.0": {
              "count": 51,
              "global": 0.05189620758483034,
              "cluster": 0.09807692307692308,
              "discrepancy": 0.04618071549209274
            },
            "10.0": {
              "count": 95,
              "global": 0.22570244127130354,
              "cluster": 0.18269230769230768,
              "discrepancy": 0.04301013357899586
            },
            "15.0": {
              "count": 26,
              "global": 0.01627514202364502,
              "cluster": 0.05,
              "discrepancy": 0.03372485797635498
            }
          }
        }
      },
      {
        "Hours per week": {
          "discrepancy": 0.31087824351297405,
          "values": {
            "40.00133111480863": {
              "count": 202,
              "global": 0.4613849224627668,
              "cluster": 0.38846153846153847,
              "discrepancy": 0.07292338400122833
            },
            "49.99140893470785": {
              "count": 84,
              "global": 0.08935974205435283,
              "cluster": 0.16153846153846155,
              "discrepancy": 0.07217871948410871
            },
            "45.035989717223615": {
              "count": 44,
              "global": 0.05972670044526332,
              "cluster": 0.08461538461538462,
              "discrepancy": 0.0248886841701213
            },
            "60.010204081632594": {
              "count": 33,
              "global": 0.04514048825426071,
              "cluster": 0.06346153846153846,
              "discrepancy": 0.01832105020727775
            },
            "20.015748031496027": {
              "count": 13,
              "global": 0.03899892522647014,
              "cluster": 0.025,
              "discrepancy": 0.013998925226470137
            }
          }
        }
      },
      {
        "fnlwgt": {
          "discrepancy": 0.21633655765392287,
          "values": {
            "155456.23004694842": {
              "count": 33,
              "global": 0.0327038231229848,
              "cluster": 0.06346153846153846,
              "discrepancy": 0.030757715338553655
            },
            "191052.1507692308": {
              "count": 35,
              "global": 0.0499001996007984,
              "cluster": 0.0673076923076923,
              "discrepancy": 0.0174074927068939
            },
            "232989.78217821787": {
              "count": 9,
              "global": 0.03101489329034239,
              "cluster": 0.01730769230769231,
              "discrepancy": 0.013707200982650082
            },
            "221189.15929203545": {
              "count": 12,
              "global": 0.034699831107016736,
              "cluster": 0.023076923076923078,
              "discrepancy": 0.011622908030093658
            },
            "401218.3561643833": {
              "count": 1,
              "global": 0.011208352525717795,
              "cluster": 0.0019230769230769232,
              "discrepancy": 0.009285275602640872
            }
          }
        }
      },
      {
        "Sex": {
          "discrepancy": 0.19375095961922306,
          "values": {
            "Female": {
              "count": 122,
              "global": 0.33149086442499615,
              "cluster": 0.23461538461538461,
              "discrepancy": 0.09687547980961153
            },
            "Male": {
              "count": 398,
              "global": 0.6685091355750038,
              "cluster": 0.7653846153846153,
              "discrepancy": 0.09687547980961153
            }
          }
        }
      },
      {
        "Workclass": {
          "discrepancy": 0.15280208813142943,
          "values": {
            "Private": {
              "count": 343,
              "global": 0.7039766620604944,
              "cluster": 0.6596153846153846,
              "discrepancy": 0.04436127744510976
            },
            "Self-emp-inc": {
              "count": 36,
              "global": 0.032243205895900504,
              "cluster": 0.06923076923076923,
              "discrepancy": 0.03698756333486873
            },
            "Local-gov": {
              "count": 43,
              "global": 0.062490403807769074,
              "cluster": 0.08269230769230769,
              "discrepancy": 0.020201903884538616
            },
            "State-gov": {
              "count": 11,
              "global": 0.03807769077230155,
              "cluster": 0.021153846153846155,
              "discrepancy": 0.0169238446184554
            },
            "Self-emp-not-inc": {
              "count": 48,
              "global": 0.0761553815446031,
              "cluster": 0.09230769230769231,
              "discrepancy": 0.016152310763089206
            }
          }
        }
      },
      {
        "Country": {
          "discrepancy": 0.0892522647013665,
          "values": {
            "United-States": {
              "count": 483,
              "global": 0.8991248272685398,
              "cluster": 0.9288461538461539,
              "discrepancy": 0.02972132657761406
            },
            "Mexico": {
              "count": 5,
              "global": 0.021188392445877474,
              "cluster": 0.009615384615384616,
              "discrepancy": 0.011573007830492858
            },
            "Puerto-Rico": {
              "count": 0,
              "global": 0.004145555043758637,
              "cluster": 0.0,
              "discrepancy": 0.004145555043758637
            },
            "Philippines": {
              "count": 1,
              "global": 0.005834484876401044,
              "cluster": 0.0019230769230769232,
              "discrepancy": 0.003911407953324121
            },
            "Columbia": {
              "count": 0,
              "global": 0.002917242438200522,
              "cluster": 0.0,
              "discrepancy": 0.002917242438200522
            }
          }
        }
      },
      {
        "Capital Loss": {
          "discrepancy": 0.08905266390296332,
          "values": {
            "-4.817479748453479e-12": {
              "count": 520,
              "global": 0.9554736680485183,
              "cluster": 1.0,
              "discrepancy": 0.0445263319514817
            },
            "1977.3999999999992": {
              "count": 0,
              "global": 0.006909258406264394,
              "cluster": 0.0,
              "discrepancy": 0.006909258406264394
            },
            "1902.0000000000002": {
              "count": 0,
              "global": 0.006295102103485337,
              "cluster": 0.0,
              "discrepancy": 0.006295102103485337
            },
            "1887.000000000001": {
              "count": 0,
              "global": 0.003992015968063872,
              "cluster": 0.0,
              "discrepancy": 0.003992015968063872
            },
            "1740.0000000000002": {
              "count": 0,
              "global": 0.001996007984031936,
              "cluster": 0.0,
              "discrepancy": 0.001996007984031936
            }
          }
        }
      },
      {
        "Race": {
          "discrepancy": 0.08695685551972976,
          "values": {
            "White": {
              "count": 467,
              "global": 0.8545984953170582,
              "cluster": 0.8980769230769231,
              "discrepancy": 0.04347842775986488
            },
            "Black": {
              "count": 36,
              "global": 0.09795793029325964,
              "cluster": 0.06923076923076923,
              "discrepancy": 0.028727161062490403
            },
            "Asian-Pac-Islander": {
              "count": 10,
              "global": 0.028404729003531397,
              "cluster": 0.019230769230769232,
              "discrepancy": 0.009173959772762166
            },
            "Other": {
              "count": 3,
              "global": 0.009058805465991094,
              "cluster": 0.0057692307692307696,
              "discrepancy": 0.0032895746967603248
            },
            "Amer-Indian-Eskimo": {
              "count": 4,
              "global": 0.00998003992015968,
              "cluster": 0.007692307692307693,
              "discrepancy": 0.002287732227851988
            }
          }
        }
      }
    ]
  }
}